HISTORY.txt
MANIFEST.in
README.txt
setup.cfg
setup.py
docs/Makefile
docs/changes.txt
docs/conf.py
docs/configuration.txt
docs/index.txt
docs/installation.txt
docs/introduction.txt
docs/usage.txt
qc/__init__.py
qc.statusmessage.egg-info/PKG-INFO
qc.statusmessage.egg-info/SOURCES.txt
qc.statusmessage.egg-info/dependency_links.txt
qc.statusmessage.egg-info/entry_points.txt
qc.statusmessage.egg-info/namespace_packages.txt
qc.statusmessage.egg-info/not-zip-safe
qc.statusmessage.egg-info/requires.txt
qc.statusmessage.egg-info/top_level.txt
qc/statusmessage/__init__.py
qc/statusmessage/message.py
qc/statusmessage/middleware.py
qc/statusmessage/tests.py