Metadata-Version: 1.0
Name: qc.statusmessage
Version: 1.0b1dev
Summary: WSGI Middleware for displaying status messages
Home-page: http://quantumcore.net
Author: Christian Scholz
Author-email: cs@comlounge.net
License: BSD License, http://quantumcore.org/license.html
Keywords: statusmessage quantumcore wsgi middleware web framework
Platform: UNKNOWN
Classifier: Programming Language :: Python
Classifier: Topic :: Software Development :: Libraries :: Python Modules
Classifier: Topic :: Internet :: WWW/HTTP :: WSGI
Classifier: Topic :: Internet :: WWW/HTTP :: WSGI :: Middleware
Classifier: Development Status :: 4 - Beta
Classifier: Environment :: Web Environment
Classifier: Intended Audience :: Developers
Classifier: Operating System :: OS Independent
Classifier: Topic :: Internet :: WWW/HTTP
